{
	"rootFolder" : 
	{
		"assets" : 
		[
			{
				"type" : "scene",
				"name" : "sponza_crytek.scn"
			},
			{
				"type" : "model",
				"name" : "sponza_crytek.mdl"
			},
			{
				"type" : "shader",
				"name" : "pbr.fx"
			}
		],
		"folders" :
		[
			"textures" : 
			{
				"assets" :
				[
					{
						"type" : "texture",
						"name" : "background.tga"
					},
					{
						"type" : "texture",
						"name" : "background_ddn.tga"
					},
					{
						"type" : "texture",
						"name" : "lion.tga"
					},
					{
						"type" : "texture",
						"name" : "lion_ddn.tga"
					},
					{
						"type" : "texture",
						"name" : "lion2_ddn.tga"
					},
					{
						"type" : "texture",
						"name" : "spnza_bricks_a_ddn.tga"
					},
					{
						"type" : "texture",
						"name" : "spnza_bricks_a_diff.tga"
					},
					{
						"type" : "texture",
						"name" : "spnza_bricks_a_spec.tga"
					},
					{
						"type" : "texture",
						"name" : "sponza_floor_a_diff.tga"
					},
					{
						"type" : "texture",
						"name" : "sponza_curtain_diff.tga"
					},
					{
						"type" : "texture",
						"name" : "sponza_curtain_blue_diff.tga"
					},
					{
						"type" : "texture",
						"name" : "sponza_curtain_green_diff.tga"
					}
				]
			},
			"materials" :
			{
				"assets" :
				[
					{
						"type" : "material",
						"name" : "blue_curtain.mat"
					},
					{
						"type" : "material",
						"name" : "green_curtain.mat"
					},
					{
						"type" : "material",
						"name" : "red_curtain.mat"
					},
					{
						"type" : "material",
						"name" : "bricks.mat"
					}
				]
			}
		]
	}
}